deep_macrofin/__init__.py
deep_macrofin/evaluations/__init__.py
deep_macrofin/evaluations/comparators.py
deep_macrofin/evaluations/conditions.py
deep_macrofin/evaluations/constraint.py
deep_macrofin/evaluations/endog_equation.py
deep_macrofin/evaluations/equation.py
deep_macrofin/evaluations/formula.py
deep_macrofin/evaluations/hjb_equation.py
deep_macrofin/evaluations/loss_compute_methods.py
deep_macrofin/evaluations/system.py
deep_macrofin/event_handler.py
deep_macrofin/models/__init__.py
deep_macrofin/models/activation_types.py
deep_macrofin/models/agents.py
deep_macrofin/models/deepset.py
deep_macrofin/models/derivative_utils.py
deep_macrofin/models/dgm.py
deep_macrofin/models/endogvars.py
deep_macrofin/models/kan/KAN.py
deep_macrofin/models/kan/KANLayer.py
deep_macrofin/models/kan/LBFGS.py
deep_macrofin/models/kan/Readme.md
deep_macrofin/models/kan/Symbolic_KANLayer.py
deep_macrofin/models/kan/__init__.py
deep_macrofin/models/kan/spline.py
deep_macrofin/models/kan/utils.py
deep_macrofin/models/learnable_var.py
deep_macrofin/models/model_utils.py
deep_macrofin/models/multkan/KANLayer.py
deep_macrofin/models/multkan/LBFGS.py
deep_macrofin/models/multkan/MultKAN.py
deep_macrofin/models/multkan/Readme.md
deep_macrofin/models/multkan/Symbolic_KANLayer.py
deep_macrofin/models/multkan/__init__.py
deep_macrofin/models/multkan/compiler.py
deep_macrofin/models/multkan/hypothesis.py
deep_macrofin/models/multkan/mult_symbol.png
deep_macrofin/models/multkan/spline.py
deep_macrofin/models/multkan/sum_symbol.png
deep_macrofin/models/multkan/utils.py
deep_macrofin/models/resnet.py
deep_macrofin/pde_model.py
deep_macrofin/pde_model_time_step.py
deep_macrofin/utils.py
deep_macrofin-0.4.0.dist-info/METADATA
deep_macrofin-0.4.0.dist-info/WHEEL
deep_macrofin-0.4.0.dist-info/licenses/LICENSE
deep_macrofin-0.4.0.dist-info/RECORD
