Metadata-Version: 2.4
Name: deep_macrofin
Version: 0.4.0
Summary: Deep neural network for solving continuous time economic models
License: MIT
License-File: LICENSE
Author: Yuntao Wu
Author-email: winstonyt.wu@mail.utoronto.ca
Requires-Python: >=3.9,<4.0
Classifier: License :: OSI Approved :: MIT License
Classifier: Programming Language :: Python :: 3
Classifier: Programming Language :: Python :: 3.9
Classifier: Programming Language :: Python :: 3.10
Classifier: Programming Language :: Python :: 3.11
Classifier: Programming Language :: Python :: 3.12
Classifier: Programming Language :: Python :: 3.13
Classifier: Programming Language :: Python :: 3.14
Requires-Dist: matplotlib (>=3.9.0,<4.0.0)
Requires-Dist: numpy (<2)
Requires-Dist: pandas (>=2.2.2,<3.0.0)
Requires-Dist: scikit-learn (>=1.3.2,<2.0.0)
Requires-Dist: sympy (>=1.12,<2.0)
Requires-Dist: torch (>=2.3.0,<3.0.0)
Requires-Dist: tqdm (>=4.66.4,<5.0.0)
Project-URL: Documentation, https://rotmanfinhub.github.io/deep-macrofin
Project-URL: Homepage, https://github.com/rotmanfinhub/deep-macrofin
Project-URL: Repository, https://github.com/rotmanfinhub/deep-macrofin
